{
  "resourceType": "StructureDefinition",
  "id": "cimi-encounter-EncounterClass-model",
  "text": {
    "status": "generated",
    "div": "<div xmlns=\"http://www.w3.org/1999/xhtml\">\n  <p><b>ODH EncounterClass Logical Model</b></p>\n  <p>Concepts representing classification of patient encounter such as ambulatory (outpatient), inpatient, emergency, home health or others due to local variations.</p>\n</div>"
  },
  "url": "http://hl7.org/fhir/us/odh/StructureDefinition/cimi-encounter-EncounterClass-model",
  "identifier": [
    {
      "system": "http://hl7.org/fhir/us/odh",
      "value": "cimi.encounter.EncounterClass"
    }
  ],
  "name": "EncounterClassModel",
  "title": "ODH EncounterClass Logical Model",
  "status": "draft",
  "date": "2018-08-13",
  "publisher": "HL7",
  "contact": [
    {
      "telecom": [
        {
          "system": "url",
          "value": "http://standardhealthrecord.org"
        }
      ]
    }
  ],
  "description": "Concepts representing classification of patient encounter such as ambulatory (outpatient), inpatient, emergency, home health or others due to local variations.",
  "kind": "logical",
  "abstract": false,
  "type": "cimi-encounter-EncounterClass-model",
  "baseDefinition": "http://hl7.org/fhir/StructureDefinition/Element",
  "derivation": "specialization",
  "snapshot": {
    "element": [
      {
        "id": "cimi-encounter-EncounterClass-model",
        "path": "cimi-encounter-EncounterClass-model",
        "definition": "Concepts representing classification of patient encounter such as ambulatory (outpatient), inpatient, emergency, home health or others due to local variations.",
        "min": 0,
        "max": "*",
        "base": {
          "path": "cimi-encounter-EncounterClass-model",
          "min": 0,
          "max": "*"
        },
        "mustSupport": false,
        "isModifier": false,
        "isSummary": false
      },
      {
        "id": "cimi-encounter-EncounterClass-model.value",
        "path": "cimi-encounter-EncounterClass-model.value",
        "short": "Code representing concepts representing classification of patient encounter such as ambulatory (outpatient), inpatient, emergency, home health or others due to local variations.",
        "definition": "Code representing concepts representing classification of patient encounter such as ambulatory (outpatient), inpatient, emergency, home health or others due to local variations.",
        "alias": [
          "codeableConcept"
        ],
        "min": 1,
        "max": "1",
        "base": {
          "path": "cimi-encounter-EncounterClass-model.value",
          "min": 1,
          "max": "1"
        },
        "type": [
          {
            "code": "Coding"
          }
        ],
        "mustSupport": false,
        "isModifier": false,
        "isSummary": false
      }
    ]
  },
  "differential": {
    "element": [
      {
        "id": "cimi-encounter-EncounterClass-model",
        "path": "cimi-encounter-EncounterClass-model",
        "definition": "Concepts representing classification of patient encounter such as ambulatory (outpatient), inpatient, emergency, home health or others due to local variations.",
        "min": 0,
        "max": "*",
        "base": {
          "path": "cimi-encounter-EncounterClass-model",
          "min": 0,
          "max": "*"
        },
        "mustSupport": false,
        "isModifier": false,
        "isSummary": false
      },
      {
        "id": "cimi-encounter-EncounterClass-model.value",
        "path": "cimi-encounter-EncounterClass-model.value",
        "short": "Code representing concepts representing classification of patient encounter such as ambulatory (outpatient), inpatient, emergency, home health or others due to local variations.",
        "definition": "Code representing concepts representing classification of patient encounter such as ambulatory (outpatient), inpatient, emergency, home health or others due to local variations.",
        "alias": [
          "codeableConcept"
        ],
        "min": 1,
        "max": "1",
        "base": {
          "path": "cimi-encounter-EncounterClass-model.value",
          "min": 1,
          "max": "1"
        },
        "type": [
          {
            "code": "Coding"
          }
        ],
        "mustSupport": false,
        "isModifier": false,
        "isSummary": false
      }
    ]
  }
}